netdata-airflow-utils/__init__.py
netdata-airflow-utils/_nbdev.py
netdata-airflow-utils/core.py
netdata_airflow_utils/__init__.py
netdata_airflow_utils/_nbdev.py
netdata_airflow_utils/airflow.py
netdata_airflow_utils/bigquery.py
netdata_airflow_utils/core.py
netdata_airflow_utils/datahub.py
netdata_airflow_utils/utils.py
netdata_airflow_utils-0.0.4.dist-info/LICENSE
netdata_airflow_utils-0.0.4.dist-info/METADATA
netdata_airflow_utils-0.0.4.dist-info/WHEEL
netdata_airflow_utils-0.0.4.dist-info/entry_points.txt
netdata_airflow_utils-0.0.4.dist-info/top_level.txt
netdata_airflow_utils-0.0.4.dist-info/RECORD
