Metadata-Version: 2.1
Name: netdata-airflow-utils
Version: 0.0.4
Summary: Airflow helper utils used at Netdata.
Home-page: https://github.com/netdata/netdata_airflow_utils/tree/master/
Author: andrewm4894
Author-email: andrewmaguire@netdata.cloud
License: Apache Software License 2.0
Keywords: netdata
Platform: UNKNOWN
Classifier: Development Status :: 3 - Alpha
Classifier: Intended Audience :: Developers
Classifier: Natural Language :: English
Classifier: Programming Language :: Python :: 3.6
Classifier: Programming Language :: Python :: 3.7
Classifier: Programming Language :: Python :: 3.8
Classifier: License :: OSI Approved :: Apache Software License
Requires-Python: >=3.6
Requires-Dist: acryl-datahub[airflow]
Requires-Dist: apache-airflow-providers-google
Requires-Dist: packaging
Requires-Dist: pip
Provides-Extra: dev
